README.md
setup.cfg
setup.py
NNS_RPY2_ScikitLearn.egg-info/PKG-INFO
NNS_RPY2_ScikitLearn.egg-info/SOURCES.txt
NNS_RPY2_ScikitLearn.egg-info/dependency_links.txt
NNS_RPY2_ScikitLearn.egg-info/requires.txt
NNS_RPY2_ScikitLearn.egg-info/top_level.txt
nns_rpy2/__init__.py
nns_rpy2/nns.py